labyrinth/__init__.py
labyrinth/data
labyrinth/function.py
labyrinth/main.py
labyrinth/img/bg.png
labyrinth/img/item.png
labyrinth/img/keeper.png
labyrinth/img/player.png
labyrinth/img/tile.png
labyrinth/img/wall_background.png
nz_labyrinth-3.5.dist-info/DESCRIPTION.rst
nz_labyrinth-3.5.dist-info/METADATA
nz_labyrinth-3.5.dist-info/RECORD
nz_labyrinth-3.5.dist-info/WHEEL
nz_labyrinth-3.5.dist-info/metadata.json
nz_labyrinth-3.5.dist-info/top_level.txt
