Metadata-Version: 2.0
Name: nz-labyrinth
Version: 3.5
Summary: Help Mc Gyver to leave the maze
Home-page: https://github.com/Hyperyon/p3-labyrinthe
Author: Nico Zhan
Author-email: nicozhan@hyperloop.fr
License: UNKNOWN
Platform: UNKNOWN
Classifier: Programming Language :: Python
Classifier: Operating System :: OS Independent
Classifier: Programming Language :: Python :: 3.5
Requires-Dist: pygame (==1.9.3)
